lavuefilters/__init__.py
lavuefilters/h5pyplugins.py
lavuefilters/memplugins.py
lavuefilters-1.2.5.dist-info/LICENSE
lavuefilters-1.2.5.dist-info/METADATA
lavuefilters-1.2.5.dist-info/WHEEL
lavuefilters-1.2.5.dist-info/top_level.txt
lavuefilters-1.2.5.dist-info/RECORD
