Metadata-Version: 2.1
Name: lavuefilters
Version: 1.2.5
Summary: Live image viewer application for photon science detectors: plugins
Home-page: https://github.com/jkotan/lavuefilters
Author: Jan Kotanski
Author-email: jan.kotanski@desy.de
License: GPLv2
Keywords: live viewer nexus writer plugin
Classifier: Development Status :: 5 - Production/Stable
Classifier: Intended Audience :: Science/Research
Classifier: Topic :: Scientific/Engineering :: Physics
Classifier: Topic :: Software Development :: Libraries :: Python Modules
Classifier: License :: OSI Approved :: GNU General Public License v2 (GPLv2)
Classifier: Programming Language :: Python :: 2.7
Classifier: Programming Language :: Python :: 3
Classifier: Programming Language :: Python :: 3.4
Classifier: Programming Language :: Python :: 3.5
Classifier: Programming Language :: Python :: 3.6
Classifier: Programming Language :: Python :: 3.7
Classifier: Programming Language :: Python :: 3.8
Classifier: Programming Language :: Python :: 3.9
Classifier: Programming Language :: Python :: 3.10
Classifier: Programming Language :: Python :: 3.11
License-File: LICENSE
Requires-Dist: h5py
Requires-Dist: numpy (>1.6.0)
Requires-Dist: scipy
